{
    "layers": [
        { "name": "default" }, 
        { "name": "tiled", "grid": "tiled" }
    ],
    "grids": [
        { "name": "tiled", "x": {"x": 10, "y": 0}, "y": { "x": 0, "y": 10}}
    ],
    "entities": [
        {
            "save": true,
            "type": "some",
            "x": 10,
            "y": 10
        },
        {
            "save": true,
            "type": "some",
            "x": 20,
            "y": 20
        },
        {
            "save": true,
            "type": "other",
            "x": 20,
            "y": 30
        }
    ]
}
